{
  "type_description_msg": {
    "type_description": {
      "type_name": "navigation_interfaces/action/GenerateInformation_FeedbackMessage",
      "fields": [
        {
          "name": "goal_id",
          "type": {
            "type_id": 1,
            "capacity": 0,
            "string_capacity": 0,
            "nested_type_name": "unique_identifier_msgs/msg/UUID"
          },
          "default_value": ""
        },
        {
          "name": "feedback",
          "type": {
            "type_id": 1,
            "capacity": 0,
            "string_capacity": 0,
            "nested_type_name": "navigation_interfaces/action/GenerateInformation_Feedback"
          },
          "default_value": ""
        }
      ]
    },
    "referenced_type_descriptions": [
      {
        "type_name": "navigation_interfaces/action/GenerateInformation_Feedback",
        "fields": [
          {
            "name": "provisional_content",
            "type": {
              "type_id": 17,
              "capacity": 0,
              "string_capacity": 0,
              "nested_type_name": ""
            },
            "default_value": ""
          }
        ]
      },
      {
        "type_name": "unique_identifier_msgs/msg/UUID",
        "fields": [
          {
            "name": "uuid",
            "type": {
              "type_id": 51,
              "capacity": 16,
              "string_capacity": 0,
              "nested_type_name": ""
            },
            "default_value": ""
          }
        ]
      }
    ]
  },
  "type_hashes": [
    {
      "type_name": "navigation_interfaces/action/GenerateInformation_FeedbackMessage",
      "hash_string": "RIHS01_6203e769df90f40a64b11e2c69efe1bd731f4247da98221c87ff7673444e746f"
    },
    {
      "type_name": "navigation_interfaces/action/GenerateInformation_Feedback",
      "hash_string": "RIHS01_48fbfd24ab0a11d16c0505e53af080b6e7cc80d571d57fa3f095d7b48eafb0e3"
    },
    {
      "type_name": "unique_identifier_msgs/msg/UUID",
      "hash_string": "RIHS01_1b8e8aca958cbea28fe6ef60bf6c19b683c97a9ef60bb34752067d0f2f7ab437"
    }
  ]
}